{
  "hash" : "e7105c43ada45c9f6e0006854ef1a1d95249231d",
  "plugins" : {
    "total" : {
      "statistic" : {
        "total" : 24,
        "passed" : 21,
        "pending" : 0,
        "canceled" : 0,
        "failed" : 3,
        "broken" : 0
      },
      "time" : {
        "start" : 1474727738205,
        "stop" : 1474727738302,
        "duration" : 97
      }
    },
    "defects" : {
      "totalCount" : 3,
      "items" : [ {
        "count" : 1,
        "uid" : "32b7a4cb701ab9a0",
        "message" : "AssertionError: expected:<1333> but was:<1>",
        "status" : "FAILED"
      }, {
        "count" : 1,
        "uid" : "59d981c81b2f0748",
        "message" : "AssertionError: expected:<543> but was:<-543>",
        "status" : "FAILED"
      }, {
        "count" : 1,
        "uid" : "6d98227cde24fb84",
        "message" : "AssertionError: expected:<1.3> but was:<1.5>",
        "status" : "FAILED"
      } ]
    },
    "xunit" : {
      "totalCount" : 1,
      "items" : [ {
        "uid" : "ef56d6645f6ecfdc",
        "title" : "Operation test suite",
        "statistic" : {
          "total" : 24,
          "passed" : 21,
          "pending" : 0,
          "canceled" : 0,
          "failed" : 3,
          "broken" : 0
        }
      } ]
    },
    "behaviors" : {
      "totalCount" : 1,
      "items" : [ {
        "title" : "Without feature",
        "statistic" : {
          "total" : 24,
          "passed" : 21,
          "pending" : 0,
          "canceled" : 0,
          "failed" : 3,
          "broken" : 0
        }
      } ]
    },
    "environment" : [ ]
  }
}